env_share/__init__.py
env_share/cli.py
env_share/config.py
env_share/decryption.py
env_share/encryption.py
env_share/init.py
env_share/lib/__init__.py
env_share/lib/dotenvx_runner.py
env_share/lib/io_utils.py
env_share/lib/paths.py
env_share/lib/validation.py
dxsync-0.2.0.dist-info/METADATA
dxsync-0.2.0.dist-info/WHEEL
dxsync-0.2.0.dist-info/entry_points.txt
dxsync-0.2.0.dist-info/licenses/LICENSE
dxsync-0.2.0.dist-info/RECORD
