Metadata-Version: 2.4
Name: dxsync
Version: 0.2.0
Summary: CLI tool for syncing encrypted .env files across teams using dotenvx
Project-URL: Homepage, https://github.com/ramusuco/dotenvx-sync
Project-URL: Repository, https://github.com/ramusuco/dotenvx-sync
Author: ramusuco
License-Expression: MIT
License-File: LICENSE
Keywords: dotenv,dotenvx,encryption,env,share
Classifier: Development Status :: 3 - Alpha
Classifier: Environment :: Console
Classifier: Intended Audience :: Developers
Classifier: License :: OSI Approved :: MIT License
Classifier: Programming Language :: Python :: 3
Classifier: Programming Language :: Python :: 3.11
Classifier: Programming Language :: Python :: 3.12
Classifier: Topic :: Security :: Cryptography
Classifier: Topic :: Software Development :: Build Tools
Requires-Python: >=3.11
Requires-Dist: click>=8.0.0
Provides-Extra: dev
Requires-Dist: pytest>=7.0.0; extra == 'dev'
